gaend/__init__.py
gaend/docs.py
gaend/elastic.py
gaend/endpoint.py
gaend/generator.py
gaend/js.py
gaend/main.py
gaend/models.py
gaend/props.py
gaend/queue.py
gaend/routes.py
gaend/state.py
gaend/templates/documentation.html
gaend-1.0.0.dev14.dist-info/DESCRIPTION.rst
gaend-1.0.0.dev14.dist-info/LICENSE.txt
gaend-1.0.0.dev14.dist-info/METADATA
gaend-1.0.0.dev14.dist-info/RECORD
gaend-1.0.0.dev14.dist-info/WHEEL
gaend-1.0.0.dev14.dist-info/metadata.json
gaend-1.0.0.dev14.dist-info/top_level.txt
